ninja_apikey/__init__.py
ninja_apikey/admin.py
ninja_apikey/apps.py
ninja_apikey/hashers.py
ninja_apikey/models.py
ninja_apikey/security.py
ninja_apikey/migrations/0001_initial.py
ninja_apikey/migrations/0002_alter_apikey_hashed_key.py
ninja_apikey/migrations/__init__.py
ninja_apikey/tests/test_admin.py
ninja_apikey/tests/test_hashers_sha256.py
ninja_apikey/tests/test_models.py
ninja_apikey/tests/test_security.py
ninja_api_key-2.0.0.dist-info/licenses/LICENSE
ninja_api_key-2.0.0.dist-info/WHEEL
ninja_api_key-2.0.0.dist-info/METADATA
ninja_api_key-2.0.0.dist-info/RECORD
